explainmath/__init__.py
explainmath/value.py
explainmath-0.1.1.dist-info/METADATA
explainmath-0.1.1.dist-info/WHEEL
explainmath-0.1.1.dist-info/top_level.txt
explainmath-0.1.1.dist-info/RECORD
