Metadata-Version: 2.4
Name: explainmath
Version: 0.1.1
Summary: A tiny library that catches invalid math operations and explains why they failed.
Author-email: FraDevSae <your@email.com>
License-Expression: MIT
Requires-Python: >=3.8
